usfm2osis-0.6.1.data/scripts/usfm2osis.py
usfm2osis-0.6.1.data/scripts/usfmtags.py
usfm2osis/util.py
usfm2osis/_compat.py
usfm2osis/__init__.py
usfm2osis/bookdata.py
usfm2osis/convert.py
usfm2osis/sort.py
usfm2osis-0.6.1.dist-info/DESCRIPTION.rst
usfm2osis-0.6.1.dist-info/METADATA
usfm2osis-0.6.1.dist-info/metadata.json
usfm2osis-0.6.1.dist-info/WHEEL
usfm2osis-0.6.1.dist-info/RECORD
usfm2osis-0.6.1.dist-info/top_level.txt
