Metadata-Version: 2.0
Name: usfm2osis
Version: 0.6.1
Summary: Tools for converting Bibles from USFM to OSIS XML
Home-page: https://github.com/chrislit/usfm2osis
Author: Christopher C. Little
Author-email: chrisclittle+usfm2osis@gmail.com
License: GPLv3+
Download-URL: https://github.com/chrislit/usfm2osis/archive/master.zip
Keywords: OSIS,USFM,Bible
Platform: UNKNOWN
Classifier: Programming Language :: Python
Classifier: Programming Language :: Python :: 2
Classifier: Programming Language :: Python :: 2.6
Classifier: Programming Language :: Python :: 2.7
Classifier: Programming Language :: Python :: 3
Classifier: Programming Language :: Python :: 3.2
Classifier: Programming Language :: Python :: 3.3
Classifier: Programming Language :: Python :: 3.4
Classifier: Development Status :: 4 - Beta
Classifier: License :: OSI Approved :: GNU General Public License v3 or later (GPLv3+)
Classifier: Operating System :: OS Independent
Classifier: Natural Language :: English
Classifier: Intended Audience :: Religion
Classifier: Intended Audience :: Developers
Classifier: Topic :: Religion
Classifier: Topic :: Text Processing :: Markup :: XML
